tests
kallithea_auth_google
