Metadata-Version: 1.0
Name: kallithea-auth-google
Version: 1.0.2
Summary: Kallithea google auth plugin
Home-page: https://github.com/paylogic/kallithea-google-auth
Author: Anatoly Bubenkov, Paylogic International and others
Author-email: developers@paylogic.com
License: MIT license
Platform: UNKNOWN
